pydnevnikruapi/__init__.py
pydnevnikruapi/constants.py
pydnevnikruapi/dnevnik.py
pydnevnikruapi/exceptions.py
pydnevnikruapi-0.2.0.dist-info/WHEEL
pydnevnikruapi-0.2.0.dist-info/METADATA
pydnevnikruapi-0.2.0.dist-info/RECORD
