Metadata-Version: 2.3
Name: pydnevnikruapi
Version: 0.2.0
Summary: Wrapper for dnevnik.ru API
Requires-Dist: aiohttp>=3.13.0
Requires-Python: >=3.13
